logifire/__init__.py
logifire/blowout.py
logifire/logbranch.py
logifire/logfilter.py
logifire/logformatter.py
logifire/logifire.py
logifire/handlers/__init__.py
logifire/handlers/slack.py
logifire/handlers/syslog.py
logifire-0.0.2.dist-info/LICENSE
logifire-0.0.2.dist-info/METADATA
logifire-0.0.2.dist-info/WHEEL
logifire-0.0.2.dist-info/top_level.txt
logifire-0.0.2.dist-info/RECORD
