Metadata-Version: 2.1
Name: logifire
Version: 0.0.2
Summary: Logs manager with mute log feature at different levels: process, server, cluster
Home-page: https://github.com/dparfyonov/logifire
Author: Dmitry Parfyonov
Author-email: parfyonov.dima@gmail.com
Project-URL: Bug Tracker, https://github.com/dparfyonov/logifire/issues
Classifier: Programming Language :: Python :: 3
Classifier: License :: OSI Approved :: MIT License
Classifier: Operating System :: OS Independent
Classifier: Intended Audience :: Developers
Classifier: Topic :: System :: Logging
Requires-Python: >=3.6
License-File: LICENSE
